labthings_client/__init__.py
labthings_client/affordances.py
labthings_client/discovery.py
labthings_client/json_typing.py
labthings_client/tasks.py
labthings_client/td_parsers.py
labthings_client/thing.py
labthings_client/utilities.py
labthings_client-0.2.0.dist-info/LICENSE
labthings_client-0.2.0.dist-info/WHEEL
labthings_client-0.2.0.dist-info/METADATA
labthings_client-0.2.0.dist-info/RECORD
