Metadata-Version: 2.1
Name: labthings-client
Version: 0.2.0
Summary: A simple Python client for LabThings devices
Author: jtc42
Author-email: jtc9242@gmail.com
Requires-Python: >=3.7,<4.0
Classifier: Programming Language :: Python :: 3
Classifier: Programming Language :: Python :: 3.7
Classifier: Programming Language :: Python :: 3.8
Classifier: Topic :: Internet :: WWW/HTTP
Classifier: Topic :: System :: Hardware
Requires-Dist: requests (>=2.23.0,<3.0.0)
Requires-Dist: zeroconf (>=0.26.0,<0.27.0)
